imagenie/__init__.py
imagenie/augment.py
imagenie/blur.py
imagenie/flip.py
imagenie/grayscale.py
imagenie/scale.py
imagenie-1.5.0.dist-info/LICENSE
imagenie-1.5.0.dist-info/METADATA
imagenie-1.5.0.dist-info/WHEEL
imagenie-1.5.0.dist-info/RECORD
