Metadata-Version: 2.3
Name: imagenie
Version: 1.5.0
Summary: A python package to support essential trasformations on image datasets
License: MIT
Author: Agam Sanghera, Gurmehak Kaur, Yuhan Fan, Yichun Liu
Requires-Python: >=3.11,<4.0
Classifier: License :: OSI Approved :: MIT License
Classifier: Programming Language :: Python :: 3
Classifier: Programming Language :: Python :: 3.11
Classifier: Programming Language :: Python :: 3.12
Classifier: Programming Language :: Python :: 3.13
Requires-Dist: jupyter (>=1.1.1,<2.0.0)
Requires-Dist: matplotlib (>=3.10.0,<4.0.0)
Requires-Dist: nbsphinx (>=0.9.6,<0.10.0)
Requires-Dist: opencv-python (>=4.11.0.86,<5.0.0.0)
Requires-Dist: pandoc (>=2.4,<3.0)
Requires-Dist: pillow (>=11.1.0,<12.0.0)
Requires-Dist: pypandoc (>=1.15,<2.0)
Requires-Dist: pytest (>=8.3.4,<9.0.0)
Requires-Dist: pytest-cov (>=6.0.0,<7.0.0)
Requires-Dist: sphinx (>=8.1.3,<9.0.0)
Requires-Dist: sphinx-book-theme (>=1.1.3,<2.0.0)
Requires-Dist: sphinx-rtd-theme (>=3.0.2,<4.0.0)
